{"@context":"https://linked.art/ns/v1/linked-art.json","id":"https://www.moma.org/data/person/27969","type":"Person","_label":"C.C. Langill","identified_by":[{"type":"Name","_label":"DisplayName","content":"C.C. Langill"},{"type":"Name","_label":"AlphaSortName","content":"Langill C.C."},{"type":"Identifier","content":"65710","attributed_by":[{"type":"AttributeAssignment","carried_out_by":[{"id":"https://www.moma.org/data/group/inst2","type":"Group"}]}]}],"equivalent":[{"id":"http://viaf.org/viaf/96236059","type":"Person"}]}