{"@context":"https://linked.art/ns/v1/linked-art.json","id":"https://www.moma.org/data/person/30291","type":"Person","_label":"Toni Stadler","identified_by":[{"type":"Name","_label":"DisplayName","content":"Toni Stadler"},{"type":"Name","_label":"AlphaSortName","content":"Stadler Toni"},{"type":"Identifier","content":"61597","attributed_by":[{"type":"AttributeAssignment","carried_out_by":[{"id":"https://www.moma.org/data/group/inst2","type":"Group"}]}]}],"equivalent":[{"id":"http://viaf.org/viaf/52484931","type":"Person"}]}