{"@context":"https://linked.art/ns/v1/linked-art.json","id":"https://www.moma.org/data/person/33062","type":"Person","_label":"Murray Alcosser","identified_by":[{"type":"Name","_label":"DisplayName","content":"Murray Alcosser"},{"type":"Name","_label":"AlphaSortName","content":"Alcosser Murray"},{"type":"Identifier","content":"66257","attributed_by":[{"type":"AttributeAssignment","carried_out_by":[{"id":"https://www.moma.org/data/group/inst2","type":"Group"}]}]}],"equivalent":[{"id":"http://viaf.org/viaf/96378992","type":"Person"}]}