{"@context":"https://linked.art/ns/v1/linked-art.json","id":"https://www.moma.org/data/person/58499","type":"Person","_label":"Jovi Schnell","identified_by":[{"type":"Name","_label":"DisplayName","content":"Jovi Schnell"},{"type":"Name","_label":"AlphaSortName","content":"Schnell Jovi"},{"type":"Identifier","content":"73128","attributed_by":[{"type":"AttributeAssignment","carried_out_by":[{"id":"https://www.moma.org/data/group/inst2","type":"Group"}]}]}],"equivalent":[{"id":"http://viaf.org/viaf/309815117","type":"Person"}]}