{"venues": [{"name": "42nd Venice Biennale", "filename": "42ndVeniceBiennale", "number_exhibitions": 1}, {"name": "44th Venice Biennale", "filename": "44thVeniceBiennale", "number_exhibitions": 1}, {"name": "45th Venice Biennale", "filename": "45thVeniceBiennale", "number_exhibitions": 1}, {"name": "Angel Orensanz Center", "filename": "AngelOrensanzCenter", "number_exhibitions": 1}, {"name": "Art Basel Miami Beach", "filename": "ArtBaselMiamiBeach", "number_exhibitions": 1}, {"name": "Bird S. Coler Hospital (now NYC Health + Hospitals/Coler)", "filename": "BirdSColerHospital(nowNYCHealth+HospitalsColer)", "number_exhibitions": 1}, {"name": "Bonwit Teller Building", "filename": "BonwitTellerBuilding", "number_exhibitions": 1}, {"name": "British Museum", "filename": "BritishMuseum", "number_exhibitions": 1}, {"name": "Calais", "filename": "Calais", "number_exhibitions": 1}, {"name": "Chelsea Hotel", "filename": "ChelseaHotel", "number_exhibitions": 1}, {"name": "Country Art Gallery", "filename": "CountryArtGallery", "number_exhibitions": 1}, {"name": "Danceteria", "filename": "Danceteria", "number_exhibitions": 1}, {"name": "Former Neptune Beverage Company, Coney Island", "filename": "FormerNeptuneBeverageCompany,ConeyIsland", "number_exhibitions": 1}, {"name": "Gorman Park Queens", "filename": "GormanParkQueens", "number_exhibitions": 1}, {"name": "Grand Central Terminal", "filename": "GrandCentralTerminal", "number_exhibitions": 1}, {"name": "Holland Tunnel", "filename": "HollandTunnel", "number_exhibitions": 1}, {"name": "Lausanne", "filename": "Lausanne", "number_exhibitions": 1}, {"name": "Parke-Bernet Galleries", "filename": "Parke-BernetGalleries", "number_exhibitions": 1}, {"name": "Rockefeller Guest House", "filename": "RockefellerGuestHouse", "number_exhibitions": 1}, {"name": "The Brooklyn Bridge", "filename": "TheBrooklynBridge", "number_exhibitions": 1}, {"name": "The New York Coliseum", "filename": "TheNewYorkColiseum", "number_exhibitions": 1}, {"name": "The Public Theater", "filename": "ThePublicTheater", "number_exhibitions": 1}, {"name": "The Town Hall", "filename": "TheTownHall", "number_exhibitions": 1}, {"name": "Xenon Discotheque", "filename": "XenonDiscotheque", "number_exhibitions": 1}, {"name": "Manhattan", "filename": "Manhattan", "number_exhibitions": 2}, {"name": "City Gallery", "filename": "CityGallery", "number_exhibitions": 8}, {"name": "The Idea Warehouse", "filename": "TheIdeaWarehouse", "number_exhibitions": 11}, {"name": "The Museum of Modern Art", "filename": "TheMuseumofModernArt", "number_exhibitions": 12}, {"name": "Judson Memorial Church", "filename": "JudsonMemorialChurch", "number_exhibitions": 16}, {"name": "Crown Building", "filename": "CrownBuilding", "number_exhibitions": 17}, {"name": "Reuben Gallery", "filename": "ReubenGallery", "number_exhibitions": 21}, {"name": "Brata Gallery", "filename": "BrataGallery", "number_exhibitions": 22}, {"name": "Rockefeller Center", "filename": "RockefellerCenter", "number_exhibitions": 23}, {"name": "Green Gallery", "filename": "GreenGallery", "number_exhibitions": 49}, {"name": "Hansa Gallery", "filename": "HansaGallery", "number_exhibitions": 84}, {"name": "Tanager Gallery", "filename": "TanagerGallery", "number_exhibitions": 101}, {"name": "Clocktower Gallery", "filename": "ClocktowerGallery", "number_exhibitions": 199}, {"name": "MoMA PS1", "filename": "MoMAPS1", "number_exhibitions": 815}, {"name": "MoMA", "filename": "MoMA", "number_exhibitions": 2383}]}